{"cameraMode":{"drawMode":0,"name":"Shaded","section":"Shading Mode"},"sceneLighting":true,"audioPlay":false,"sceneViewState":{"m_AlwaysRefresh":false,"showFog":true,"showSkybox":true,"showFlares":true,"showImageEffects":true,"showParticleSystems":true,"showVisualEffectGraphs":true,"m_FxEnabled":true},"in2DMode":false,"pivot":{"x":5.438877105712891,"y":2.617483377456665,"z":1.114480972290039},"rotation":{"x":-0.16838721930980683,"y":0.15367481112480164,"z":-0.02658647857606411,"w":-0.9733063578605652},"size":2.2475228309631349,"orthographic":false}